yaml2rst/__init__.py
yaml2rst/__main__.py
yaml2rst-0.3.dist-info/DESCRIPTION.rst
yaml2rst-0.3.dist-info/METADATA
yaml2rst-0.3.dist-info/RECORD
yaml2rst-0.3.dist-info/WHEEL
yaml2rst-0.3.dist-info/entry_points.txt
yaml2rst-0.3.dist-info/metadata.json
yaml2rst-0.3.dist-info/top_level.txt
