Metadata-Version: 2.0
Name: yaml2rst
Version: 0.3
Summary: A Simple Tool for Documenting YAML Files
Home-page: https://github.com/debops/yaml2rst
Author: Hartmut Goebel
Author-email: h.goebel@crazy-compilers.com
License: GPLv3+
Download-URL: https://github.com/debops/yaml2rst/releases
Keywords: YML,YAML,rst,reStructuresText,literate programming
Platform: UNKNOWN
Classifier: Development Status :: 4 - Beta
Classifier: Environment :: Console
Classifier: Intended Audience :: Developers
Classifier: Intended Audience :: System Administrators
Classifier: License :: OSI Approved :: GNU General Public License v3 or later (GPLv3+)
Classifier: Natural Language :: English
Classifier: Operating System :: OS Independent
Classifier: Programming Language :: Python :: 2
Classifier: Programming Language :: Python :: 3
Classifier: Topic :: Software Development :: Documentation
